setup.py
pywizard_remote/__init__.py
pywizard_remote/agent.py
pywizard_remote/crypt.py
pywizard_remote/transport.py
pywizard_remote.egg-info/PKG-INFO
pywizard_remote.egg-info/SOURCES.txt
pywizard_remote.egg-info/dependency_links.txt
pywizard_remote.egg-info/requires.txt
pywizard_remote.egg-info/top_level.txt
test/test_crypt.py
test/test_transport.py