Metadata-Version: 1.0
Name: pywizard-remote
Version: 0.1.2
Summary: Remote controll for pywizard.
Home-page: UNKNOWN
Author: Alex Rudakov
Author-email: ribozz@gmail.com
License: MIT
Platform: UNKNOWN
